okx/__init__.py
okx/clients.py
okx/constants.py
okx/exceptions.py
okx/utils.py
okx/restapi/Account.py
okx/restapi/Affiliate.py
okx/restapi/AlgoTrading.py
okx/restapi/BaseClient.py
okx/restapi/BlockTrading.py
okx/restapi/Broker.py
okx/restapi/CopyTrading.py
okx/restapi/Finance.py
okx/restapi/FinancialProduct.py
okx/restapi/Funding.py
okx/restapi/GridTrading.py
okx/restapi/MarketData.py
okx/restapi/PublicData.py
okx/restapi/RecurringBuy.py
okx/restapi/Rubik.py
okx/restapi/SignalTrading.py
okx/restapi/SpreadTrading.py
okx/restapi/SubAccount.py
okx/restapi/Trading.py
okx/restapi/__init__.py
okx/wsapi/Factory.py
okx/wsapi/PrivateAsync.py
okx/wsapi/PublicAsync.py
okx/wsapi/__init__.py
okx/wsapi/wsutils.py
okx_sdk-5.5.812.dist-info/licenses/LICENSE
tests/__init__.py
okx_sdk-5.5.812.dist-info/METADATA
okx_sdk-5.5.812.dist-info/WHEEL
okx_sdk-5.5.812.dist-info/top_level.txt
okx_sdk-5.5.812.dist-info/RECORD
