Metadata-Version: 2.4
Name: okx-sdk
Version: 5.5.812
Summary: Up-to-date, most-complete, well-organized, well-documented, easy-to-use OKX Exchange Rest and Websocket API SDK for Python
Home-page: https://github.com/burakoner/okx-sdk
Author: Burak Öner
Author-email: info@burakoner.com
Keywords: okx,crypto,exchange,api,sdk,stream,websocket,ws,python,bitcoin,btc,spot,futures,trade
Classifier: Programming Language :: Python :: 3
Classifier: License :: OSI Approved :: Apache Software License
Classifier: Operating System :: OS Independent
License-File: LICENSE
Requires-Dist: importlib-metadata
Requires-Dist: httpx[http2]
Requires-Dist: keyring
Requires-Dist: requests
Requires-Dist: Twisted
Requires-Dist: pyOpenSSL
Dynamic: author
Dynamic: author-email
Dynamic: classifier
Dynamic: description
Dynamic: description-content-type
Dynamic: home-page
Dynamic: keywords
Dynamic: license-file
Dynamic: requires-dist
Dynamic: summary
